[
  {
    "Name": "Agua Fire",
    "Updated": "2023-07-27",
    "Started": "2023-07-25",
    "AdminUnit": "Angeles National Forest ",
    "County": "Los Angeles",
    "Location": "Soledad Canyon, west of Acton",
    "AcresBurned": 0,
    "PercentContained": 0,
    "Longitude": -118.326389,
    "Latitude": 34.438333,
    "Type": null,
    "UniqueId": "287f3a55-d3a6-4273-ad3c-c66910a12cb9",
    "Url": "/incidents/2023/7/25/agua-fire/",
    "StartedDateOnly": null,
    "IsActive": true,
    "ExternalUrl": "https://inciweb.nwcg.gov/incident-information/caanf-agua-fire"
  },
  {
    "Name": "York Fire",
    "Updated": "2023-08-05",
    "Started": "2023-08-01",
    "AdminUnit": "Mojave National Preserve ",
    "County": "San Bernardino",
    "Location": "New York Mountains, San Bernardino County, and Clark County",
    "AcresBurned": 0,
    "PercentContained": 0,
    "Longitude": -115.317389,
    "Latitude": 35.191889,
    "Type": null,
    "UniqueId": "44335201-1bda-408e-8bed-ec84b650c770",
    "Url": "/incidents/2023/8/1/york-fire/",
    "StartedDateOnly": null,
    "IsActive": true,
    "ExternalUrl": "https://inciweb.wildfire.gov/incident-publication/camnp-2023-york-fire/york-fire-update-73123-830am"
  },
  {
    "Name": "Tecuya Fire",
    "Updated": "2023-08-04",
    "Started": "2023-08-02",
    "AdminUnit": "USFS/Los Padres National Forest",
    "County": "Kern",
    "Location": "North of Frazier Park, Tecuya Mountain",
    "AcresBurned": 0,
    "PercentContained": 0,
    "Longitude": -118.997325,
    "Latitude": 34.847129,
    "Type": null,
    "UniqueId": "3178236b-9195-40af-93c6-34e7d13f405a",
    "Url": "/incidents/2023/8/2/tecuya-fire/",
    "StartedDateOnly": null,
    "IsActive": true,
    "ExternalUrl": "https://www.fs.usda.gov/"
  },
  {
    "Name": "No Name Fire",
    "Updated": "2023-08-06",
    "Started": "2023-08-05",
    "AdminUnit": "Lead agency: Kern County Fire",
    "County": "Kern",
    "Location": "Sand Canyon Rd , southwest of Pearsonville",
    "AcresBurned": 1120,
    "PercentContained": 70,
    "Longitude": -117.8875,
    "Latitude": 35.78611,
    "Type": null,
    "UniqueId": "128eaf5b-0947-44d0-9df9-fd7975d0fe9d",
    "Url": "/incidents/2023/8/5/no-name-fire/",
    "StartedDateOnly": null,
    "IsActive": true,
    "ExternalUrl": ""
  },
  {
    "Name": "Bunnie Fire",
    "Updated": "2023-08-10",
    "Started": "2023-08-09",
    "AdminUnit": "CAL FIRE San Diego Unit",
    "County": "San Diego",
    "Location": "San Vicente Road and Chuck Wagon Road",
    "AcresBurned": 184,
    "PercentContained": 30,
    "Longitude": -116.855731,
    "Latitude": 32.994676,
    "Type": null,
    "UniqueId": "bdbc6903-5fea-4b29-9ddf-874bfd7174c8",
    "Url": "/incidents/2023/8/9/bunnie-fire/",
    "StartedDateOnly": null,
    "IsActive": true,
    "ExternalUrl": ""
  },
  {
    "Name": "Rock Fire",
    "Updated": "2023-08-10",
    "Started": "2023-08-09",
    "AdminUnit": "CAL FIRE Riverside Unit",
    "County": "Riverside",
    "Location": "Southwest of Martin St & Davis Rd, Lake Perris",
    "AcresBurned": 500,
    "PercentContained": 75,
    "Longitude": -117.150639,
    "Latitude": 33.871189,
    "Type": null,
    "UniqueId": "0a2ff66b-76bc-4671-9afe-a2023060b6d9",
    "Url": "/incidents/2023/8/9/rock-fire/",
    "StartedDateOnly": null,
    "IsActive": true,
    "ExternalUrl": ""
  },
  {
    "Name": "Dry Creek Complex",
    "Updated": "2023-08-10",
    "Started": "2023-08-10",
    "AdminUnit": "CAL FIRE Tulare Unit",
    "County": "Tulare",
    "Location": "Dry Creek Road and Mile Marker 4, northeast of Woodlake in Tulare County",
    "AcresBurned": 375,
    "PercentContained": 5,
    "Longitude": -119.0113,
    "Latitude": 36.5323,
    "Type": null,
    "UniqueId": "954a9ca6-3863-4a6f-b22f-fc6bb6fcef6c",
    "Url": "/incidents/2023/8/10/dry-creek-complex/",
    "StartedDateOnly": null,
    "IsActive": true,
    "ExternalUrl": ""
  }
]
