{
  "Incidents": [
    {
      "UniqueId": "61df1665-dbf2-4150-be54-9e94a0cbc9d3",
      "Name": "Colorado Fire ",
      "Location": "Palo Colorado Canyon, Big Sur,  south of Carmel-by-the-sea ",
      "Latitude": 36.396461,
      "Longitude": -121.880533,
      "AcresBurned": 1500,
      "FuelType": null,
      "PercentContained": 5,
      "ControlStatement": null,
      "ConditionStatement": null,
      "Counties": [
        "Monterey"
      ],
      "CountyIds": "27",
      "SearchDescription": null,
      "SearchKeywords": null,
      "AdminUnit": "Unified Command: CAL FIRE San Benito-Monterey and Mid Coast Fire",
      "Updated": "2022-01-22T08:19:59.72Z",
      "Started": "2022-01-21T17:19:00Z",
      "Extinguished": null,
      "ArchiveYear": 2022,
      "Public": true,
      "Active": true,
      "Featured": false,
      "CalFireIncident": false,
      "MajorIncident": false,
      "Final": false,
      "Status": "Active",
      "CanonicalUrl": "/incidents/2022/1/21/colorado-fire/",
      "ExternalIncidentLink": null,
      "StructuresDestroyed": null,
      "StructuresDamaged": null,
      "StructuresThreatened": null,
      "StructuresEvacuated": null,
      "PersonnelInvolved": null,
      "CrewsInvolved": null,
      "Injuries": null,
      "Fatalities": null,
      "Helicopters": null,
      "Engines": null,
      "Dozers": null,
      "WaterTenders": null,
      "AirTankers": null
    }
  ],
  "MatchedIncidentCount": 0,
  "AllAcres": 1500,
  "AllIncidentCount": 1,
  "AllFatalities": 0,
  "AllStructures": 0,
  "ListIncidents": [
    {
      "UniqueId": "61df1665-dbf2-4150-be54-9e94a0cbc9d3",
      "Name": "Colorado Fire ",
      "Location": "Palo Colorado Canyon, Big Sur,  south of Carmel-by-the-sea ",
      "Latitude": 36.396461,
      "Longitude": -121.880533,
      "AcresBurned": 1500,
      "FuelType": null,
      "PercentContained": 5,
      "ControlStatement": null,
      "ConditionStatement": null,
      "Counties": [
        "Monterey"
      ],
      "CountyIds": "27",
      "SearchDescription": null,
      "SearchKeywords": null,
      "AdminUnit": "Unified Command: CAL FIRE San Benito-Monterey and Mid Coast Fire",
      "Updated": "2022-01-22T08:19:59.72Z",
      "Started": "2022-01-21T17:19:00Z",
      "Extinguished": null,
      "ArchiveYear": 2022,
      "Public": true,
      "Active": true,
      "Featured": false,
      "CalFireIncident": false,
      "MajorIncident": false,
      "Final": false,
      "Status": "Active",
      "CanonicalUrl": "/incidents/2022/1/21/colorado-fire/",
      "ExternalIncidentLink": null,
      "StructuresDestroyed": null,
      "StructuresDamaged": null,
      "StructuresThreatened": null,
      "StructuresEvacuated": null,
      "PersonnelInvolved": null,
      "CrewsInvolved": null,
      "Injuries": null,
      "Fatalities": null,
      "Helicopters": null,
      "Engines": null,
      "Dozers": null,
      "WaterTenders": null,
      "AirTankers": null
    }
  ],
  "AllYearIncidents": [
    {
      "IncidentId": 3211,
      "UniqueId": "61df1665-dbf2-4150-be54-9e94a0cbc9d3",
      "Name": "Colorado Fire ",
      "Location": "Palo Colorado Canyon, Big Sur,  south of Carmel-by-the-sea ",
      "Latitude": 36.396461,
      "Longitude": -121.880533,
      "AcresBurnedDisplay": "1,500",
      "PercentContainedDisplay": "5%",
      "ExternalIncidentLink": "",
      "CountiesList": "Monterey",
      "UpdatedDate": "2022-01-22 08:19:59",
      "StartedDate": "2022-01-21",
      "AdminUnit": "Unified Command: CAL FIRE San Benito-Monterey and Mid Coast Fire",
      "IncidentTypeDisplay": "Wildfire",
      "Url": "https://www.fire.ca.gov/incidents/2022/1/21/colorado-fire/",
      "IsActive": "Y"
    }
  ]
}
