{
  "Incidents": [],
  "MatchedIncidentCount": 0,
  "AllAcres": 1299,
  "AllIncidentCount": 10,
  "AllFatalities": 0,
  "AllStructures": 0,
  "ListIncidents": [],
  "AllYearIncidents": [
    {
      "IncidentId": 2717,
      "UniqueId": "2347b6fb-8468-46bb-9917-d5cea3f1efdd",
      "Name": "Erbes Fire",
      "Location": "Erbes Road and Westland Place",
      "Latitude": 34.20955,
      "Longitude": -118.83967,
      "AcresBurnedDisplay": "250",
      "PercentContainedDisplay": "100%",
      "CountiesList": "Ventura",
      "UpdatedDate": "2021-01-25 13:45:12",
      "StartedDate": "2021-01-14",
      "AdminUnit": "Ventura County Fire Department",
      "IncidentTypeDisplay": "Wildfire",
      "Url": "https://www.fire.ca.gov/incidents/2021/1/14/erbes-fire/",
      "IsActive": "N"
    },
    {
      "IncidentId": 2719,
      "UniqueId": "68c11904-f38b-4aa0-ab90-b3c805c4e8cd",
      "Name": "Manzanita Fire",
      "Location": "Manzanita Lake Drive and Road 222, North of North Fork",
      "Latitude": 37.25086,
      "Longitude": -119.51982,
      "AcresBurnedDisplay": "23",
      "PercentContainedDisplay": "100%",
      "CountiesList": "Madera",
      "UpdatedDate": "2021-01-20 15:25:41",
      "StartedDate": "2021-01-19",
      "AdminUnit": "CAL FIRE Madera Mariposa Merced Unit",
      "IncidentTypeDisplay": "Wildfire",
      "Url": "https://www.fire.ca.gov/incidents/2021/1/19/manzanita-fire/",
      "IsActive": "N"
    },
    {
      "IncidentId": 2720,
      "UniqueId": "929a21bc-65a0-49b4-bc90-bfa5457987e4",
      "Name": "Bonny Doone Complex (Previously Fanning Fire)",
      "Location": "Fanning Grade and Harmony Hill Road, East of Ben Lomond",
      "Latitude": 37.08931,
      "Longitude": -122.10509,
      "AcresBurnedDisplay": "20",
      "PercentContainedDisplay": "100%",
      "CountiesList": "Santa Cruz",
      "UpdatedDate": "2021-01-21 18:38:20",
      "StartedDate": "2021-01-19",
      "AdminUnit": "CAL FIRE San Mateo Santa Cruz Unit",
      "IncidentTypeDisplay": "Wildfire",
      "Url": "https://www.fire.ca.gov/incidents/2021/1/19/bonny-doone-complex-previously-fanning-fire/",
      "IsActive": "N"
    },
    {
      "IncidentId": 2721,
      "UniqueId": "2657090b-ec47-4fbe-bc4e-400cd50a8d55",
      "Name": "North Butano Fire",
      "Location": "Off of Old Womans Creek Road , South of Loma Mar",
      "Latitude": 37.18259,
      "Longitude": -122.28823,
      "AcresBurnedDisplay": "15",
      "PercentContainedDisplay": "100%",
      "CountiesList": "San Mateo",
      "UpdatedDate": "2021-01-21 18:33:54",
      "StartedDate": "2021-01-18",
      "AdminUnit": "CAL FIRE San Mateo Santa Cruz Unit",
      "IncidentTypeDisplay": "Wildfire",
      "Url": "https://www.fire.ca.gov/incidents/2021/1/18/north-butano-fire/",
      "IsActive": "N"
    },
    {
      "IncidentId": 2722,
      "UniqueId": "9b2b5a16-52cf-4f2e-bc8a-a3af75b28522",
      "Name": "China Grade Fire",
      "Location": "China Grade Road and Foxglove Lane, Northwest of Boulder Creek",
      "Latitude": 37.17749,
      "Longitude": -122.1756,
      "AcresBurnedDisplay": "22",
      "PercentContainedDisplay": "100%",
      "CountiesList": "Santa Cruz",
      "UpdatedDate": "2021-02-18 14:11:18",
      "StartedDate": "2021-01-18",
      "AdminUnit": "CAL FIRE San Mateo Santa Cruz Unit",
      "IncidentTypeDisplay": "",
      "Url": "https://www.fire.ca.gov/incidents/2021/1/18/china-grade-fire/",
      "IsActive": "N"
    },
    {
      "IncidentId": 2776,
      "UniqueId": "75711186-5792-4c41-9309-48dbac8e667d",
      "Name": "Wolf Fire",
      "Location": "Hwy 166 along the Wind Wolves Preserve",
      "Latitude": 34.99432,
      "Longitude": -119.185309,
      "AcresBurnedDisplay": "685",
      "PercentContainedDisplay": "100%",
      "CountiesList": "Kern",
      "UpdatedDate": "2021-02-18 14:10:35",
      "StartedDate": "2021-01-19",
      "AdminUnit": "Kern County Fire Department",
      "IncidentTypeDisplay": "",
      "Url": "https://www.fire.ca.gov/incidents/2021/1/19/wolf-fire/",
      "IsActive": "N"
    },
    {
      "IncidentId": 2777,
      "UniqueId": "b38fdc2c-3108-4273-8a67-8d69bdbfb6bb",
      "Name": "72 Fire",
      "Location": "Ave 72 and Pierce St, south of Oasis",
      "Latitude": 33.52871,
      "Longitude": -116.10723,
      "AcresBurnedDisplay": "43",
      "PercentContainedDisplay": "100%",
      "CountiesList": "Riverside",
      "UpdatedDate": "2021-01-25 13:47:05",
      "StartedDate": "2021-01-19",
      "AdminUnit": "CAL FIRE/ Riverside County Fire Department",
      "IncidentTypeDisplay": "Wildfire",
      "Url": "https://www.fire.ca.gov/incidents/2021/1/19/72-fire/",
      "IsActive": "N"
    },
    {
      "IncidentId": 2778,
      "UniqueId": "79aca6f4-ee40-44e8-9dff-069c36c36fc1",
      "Name": "Towsley Fire",
      "Location": "Towsley Canyon Road and I-5, South of Santa Clarita",
      "Latitude": 34.3585229,
      "Longitude": -118.5553174,
      "AcresBurnedDisplay": "184",
      "PercentContainedDisplay": "100%",
      "CountiesList": "Los Angeles",
      "UpdatedDate": "2021-02-18 14:10:17",
      "StartedDate": "2021-01-19",
      "AdminUnit": "Los Angeles County Fire Department",
      "IncidentTypeDisplay": "",
      "Url": "https://www.fire.ca.gov/incidents/2021/1/19/towsley-fire/",
      "IsActive": "N"
    },
    {
      "IncidentId": 2779,
      "UniqueId": "7be84564-edf7-4724-99ba-5c1ee7f86e30",
      "Name": "Panther Ridge Fire",
      "Location": "Stapp Rd and Hwy 9, north of Boulder Creek",
      "Latitude": 37.18381,
      "Longitude": -122.13372,
      "AcresBurnedDisplay": "20",
      "PercentContainedDisplay": "100%",
      "CountiesList": "Santa Cruz",
      "UpdatedDate": "2021-02-19 11:21:26",
      "StartedDate": "2021-01-19",
      "AdminUnit": "CAL FIRE San Mateo-Santa Cruz Unit",
      "IncidentTypeDisplay": "Wildfire",
      "Url": "https://www.fire.ca.gov/incidents/2021/1/19/panther-ridge-fire/",
      "IsActive": "N"
    },
    {
      "IncidentId": 2781,
      "UniqueId": "1ebddf4e-0190-4363-a858-ac789206b5fd",
      "Name": "Freedom Fire",
      "Location": "Freedom Boulevard and Hames Road, East of Aptos.",
      "Latitude": 36.98767,
      "Longitude": -121.83627,
      "AcresBurnedDisplay": "37",
      "PercentContainedDisplay": "100%",
      "CountiesList": "Santa Cruz",
      "UpdatedDate": "2021-03-02 20:32:36",
      "StartedDate": "2021-01-19",
      "AdminUnit": "CAL FIRE San Mateo  Santa Cruz Unit",
      "IncidentTypeDisplay": "Wildfire",
      "Url": "https://www.fire.ca.gov/incidents/2021/1/19/freedom-fire/",
      "IsActive": "N"
    }
  ]
}
